{
  "generated_at": "2026-03-30T08:06:22+09:00",
  "total_count": 34,
  "briefing": {
    "highlights": [
      "[전북도민일보 - 전체] 국영석 후보, 민주당 완주군수 경선 참여하나?",
      "[전북도민일보 - 진안] 진안군수 민주당 후보 합동 연설회",
      "[정책브리핑 - 새만금개발청] 김민석 국무총리, 새만금개발청 방문",
      "[연합뉴스 - 정치] '컷오프' 국힘 주호영 \"잘못된 공천이 보수 무너뜨려…개혁해야\"",
      "[전북도민일보 - 진안] 진안군, AI 교육으로 농업인 역량 키운다"
    ],
    "campaign_advice": "전북·진안 경선 이슈는 ‘공정한 공천/경선’ 요구가 강해지고 있어, 캠프는 심사·경선 기준과 일정, 검증 원칙을 먼저 공개해 불신을 줄이는 게 유리합니다. 동시에 유가·물가 상승, 지역 의료 인력(지역의사제) 같은 민생 의제를 핵심 메시지로 잡고 전통시장·농촌 현장에서 ‘즉시 실행 가능한 약속(지원·제도개선)’을 제시하세요.",
    "farm_advice": "유류비 상승과 에너지 비용 부담이 커지는 흐름이어서, 면세유·물류 공동구매·시설원예 에너지 효율(스마트 제어) 지원을 묶은 ‘농가 경영비 절감’ 대책을 우선 점검하세요. 또한 진안군의 AI 교육처럼 디지털 홍보·판매 역량을 실제 매출로 연결(공동브랜드, 라이브커머스, 가공·체험 연계)하는 프로그램을 확대하면 효과가 큽니다."
  },
  "categories": {
    "선거/캠페인": [
      {
        "title": "민주당 도당 공관위, 정청래 당 대표 지침과도 맞설까? 관심 쇄도",
        "source": "전북도민일보 - 전체",
        "link": "http://www.domin.co.kr/news/articleView.html?idxno=1550233",
        "published": "2026-03-29",
        "summary": "정청래 민주당 대표가 시·도당 공천관리위에 후보들의 경선 참여를 최대한 보장하라는 지침을 내리면서, 전북도당 공관위의 공천 방식과 충돌 가능성이 주목된다. 최근 컷오프 등 공천 과정에서 파열음이 이어진 만큼 후속 조정과 반발 수습 여부가 관건이다.",
        "keywords": [
          "민주당",
          "전북도당",
          "공천관리위원회",
          "경선 보장",
          "정청래"
        ],
        "ai_insight": "경선 참여 보장 요구가 커지면 ‘공정·투명 공천’ 프레임이 핵심 이슈가 된다. 캠프는 절차·기준 공개, 후보 검증 원칙을 선제 제시해 지지층 불신을 줄이는 방향으로 대응하는 게 유리하다."
      },
      {
        "title": "전북 민주당 권리당원 19만 명",
        "source": "전북도민일보 - 전체",
        "link": "http://www.domin.co.kr/news/articleView.html?idxno=1550164",
        "published": "2026-03-29",
        "summary": "민주당 전북도당은 6·3 지방선거 경선 투표권을 가진 권리당원이 19만 명이라고 밝혔다. 전북 인구 대비 비중이 높아 경선 동원과 조직 관리가 선거 판세에 큰 영향을 미칠 전망이다.",
        "keywords": [
          "전북 민주당",
          "권리당원",
          "경선",
          "지방선거",
          "투표권"
        ],
        "ai_insight": "권리당원 비중이 큰 지역은 ‘조직 선거’가 강해져 메시지보다도 접촉·참여 설계가 성패를 좌우한다. 캠페인은 당원 대상 정책 간담회, 투표 독려 루틴, 온라인 소통 채널을 표준화해 이탈을 줄이는 전략이 필요하다."
      },
      {
        "title": "국영석 후보, 민주당 완주군수 경선 참여하나?",
        "source": "전북도민일보 - 전체",
        "link": "http://www.domin.co.kr/news/articleView.html?idxno=1550214",
        "published": "2026-03-29",
        "summary": "민주당 완주군수 공천에서 도당 공관위의 부적격 판정을 받은 국영석 후보가 경선에 참여할 가능성이 거론된다. 정청래 대표가 경선 참여 최대 보장을 지침으로 내린 것으로 알려지며 공천 구도가 다시 흔들릴 수 있다는 전망이다.",
        "keywords": [
          "완주군수",
          "민주당",
          "공천",
          "부적격",
          "경선 참여"
        ],
        "ai_insight": "공천 번복 가능성이 커지면 ‘공정성’과 ‘후보 경쟁력’ 논쟁이 동시에 확대된다. 캠프는 네거티브보다 검증 기준과 지역 현안 해결 능력을 중심으로 프레임을 전환해 중도층 피로도를 낮춰야 한다."
      },
      {
        "title": "진안군수 민주당 후보 합동 연설회",
        "source": "전북도민일보 - 진안",
        "link": "http://www.domin.co.kr/news/articleView.html?idxno=1550253",
        "published": "2026-03-29",
        "summary": "진안군 청소년수련관에서 더불어민주당 진안군수 경선 후보 합동 연설회가 열려 예비후보들이 공약과 비전을 발표했다. 교통 인프라, 청사 이전, 지역 개발, 스포츠 시설 확충 등 지역 현안을 중심으로 경쟁이 전개됐다.",
        "keywords": [
          "진안군수",
          "민주당",
          "합동연설회",
          "지방선거",
          "공약"
        ],
        "ai_insight": "지역 경선은 공약의 ‘실행 가능성’이 핵심이므로 재원·일정·우선순위를 숫자로 제시해야 한다. 농업 비중이 큰 진안에서는 교통·주거 공약과 함께 농가 소득·농업 인력·유통 개선을 결합한 패키지가 경쟁력을 높인다."
      },
      {
        "title": "김민석 국무총리, 새만금개발청 방문",
        "source": "정책브리핑 - 새만금개발청",
        "link": "https://www.korea.kr/briefing/pressReleaseView.do?newsId=156747477&call_from=rsslink",
        "published": "2026-03-05",
        "summary": "김민석 국무총리가 새만금개발청을 방문해 현대차그룹의 새만금 투자계획을 보고 받고 새만금 기본계획 추진 현황을 점검했다. 정부 차원의 인력양성·인프라 지원 의지와 개발 속도·방향에 대한 논의가 이뤄졌다는 내용이다.",
        "keywords": [
          "국무총리",
          "새만금개발청",
          "현대차 투자",
          "기본계획",
          "정부 지원"
        ],
        "ai_insight": "중앙정부 방문은 ‘속도전’ 신호로 읽히기 쉬워, 지역은 환경·교통·주거 같은 부작용 관리 대책을 요구한다. 농업 분야는 개발과 농지·수자원 관리가 충돌할 수 있어, 농생명용지 운영 원칙과 농가 참여 모델을 선제적으로 제시하는 것이 중요하다."
      },
      {
        "title": "강기정 후보 \"광주 원도심에 AI 거리 조성\"",
        "source": "연합뉴스 - 정치",
        "link": "https://www.yna.co.kr/view/AKR20260329041000054",
        "published": "2026-03-29",
        "summary": "강기정 민주당 예비후보가 광주 원도심 공동화 문제 해결을 위해 AI 거리를 조성하겠다는 구상을 밝혔다. 원도심 활성화를 산업·기술 전략과 결합해 도시 재생의 동력으로 삼겠다는 취지다.",
        "keywords": [
          "광주",
          "원도심",
          "AI 거리",
          "도시재생",
          "선거 공약"
        ],
        "ai_insight": "AI·도시재생은 ‘구호’로 보이기 쉬워 민간 투자, 입주 기업, 일자리 규모를 구체화해야 한다. 전북 캠페인에서도 새만금·전주 구도심·혁신도시 등을 묶어 ‘지역형 AI 산업’ 모델을 제시할 때 수치·일정이 필수다."
      },
      {
        "title": "[인터뷰] 오세훈 \"대통령보다 5선 서울시장 택하겠다…진심 통할 것\"",
        "source": "연합뉴스 - 정치",
        "link": "https://www.yna.co.kr/view/AKR20260329031500001",
        "published": "2026-03-29",
        "summary": "오세훈 서울시장이 인터뷰에서 대통령 도전보다 5선 서울시장에 집중하겠다는 입장을 밝혔다. 시정 성과와 연속성을 내세우며 유권자에게 진정성을 강조하는 메시지로 읽힌다.",
        "keywords": [
          "오세훈",
          "서울시장",
          "5선",
          "선거",
          "인터뷰"
        ],
        "ai_insight": "‘연속성’ 프레임은 지자체 선거에서 유효하지만, 현안 해결 성과를 증명할 데이터가 필요하다. 전북·진안 캠페인도 임기 내 완수 가능한 핵심 과제를 3~5개로 압축해 ‘끝까지 책임’ 메시지로 설계하는 게 효과적이다."
      },
      {
        "title": "정청래, 노량진 수산시장 민생방문…'5부제' 따라 대중교통 출근",
        "source": "연합뉴스 - 정치",
        "link": "https://www.yna.co.kr/view/AKR20260329041400001",
        "published": "2026-03-29",
        "summary": "정청래 민주당 대표가 노량진 수산시장을 찾아 민생 행보를 이어간다는 내용이다. 대중교통 출근 등 상징적 행동을 통해 생활물가·자영업 현안을 부각하려는 움직임으로 보인다.",
        "keywords": [
          "정청래",
          "노량진 수산시장",
          "민생 행보",
          "물가",
          "자영업"
        ],
        "ai_insight": "민생 방문은 지역에서도 반복 가능한 포맷이라, 전통시장·농산물 도매시장 현장 점검과 즉시 실행 가능한 약속(수수료·주차·상인 지원)을 세트로 제시하면 파급이 크다. 농업 측면에선 수산시장처럼 ‘유통 현장’ 이슈를 농산물 유통비 절감 공약과 연결할 수 있다."
      },
      {
        "title": "김부겸, 오늘 출마 선언…'보수 심장' 대구 선거판 흔든다",
        "source": "연합뉴스 - 정치",
        "link": "https://www.yna.co.kr/view/AKR20260329032700053",
        "published": "2026-03-29",
        "summary": "김부겸 전 국무총리가 대구시장 선거 출마를 공식 선언한다는 소식이다. 전통적으로 보수 성향이 강한 지역의 선거 구도에 변수가 될 가능성이 제기된다.",
        "keywords": [
          "김부겸",
          "대구시장",
          "출마 선언",
          "지방선거",
          "선거 구도"
        ],
        "ai_insight": "거물급 출마는 지역 선거판을 재편하므로, 전북에서도 ‘인지도 vs 지역밀착’ 경쟁 구도를 어떻게 만들지 전략이 필요하다. 캠페인은 지역 현안(의료·교통·농업 소득)을 선명하게 잡아 전국 이슈에 휩쓸리지 않도록 의제 주도권을 유지해야 한다."
      },
      {
        "title": "'컷오프' 국힘 주호영 \"잘못된 공천이 보수 무너뜨려…개혁해야\"",
        "source": "연합뉴스 - 정치",
        "link": "https://www.yna.co.kr/view/AKR20260329045900001",
        "published": "2026-03-29",
        "summary": "국민의힘 주호영 의원이 대구시장 경선에서 컷오프된 것과 관련해 공천 관행을 비판하며 개혁 필요성을 주장했다. 당내 공천 갈등이 외부로 표면화되는 양상이다.",
        "keywords": [
          "국민의힘",
          "주호영",
          "컷오프",
          "공천 갈등",
          "개혁"
        ],
        "ai_insight": "공천 잡음은 ‘정치 불신’으로 번지기 쉬워, 캠페인은 절차 공정성과 후보 검증을 생활정치 성과로 환원해야 한다. 농업·민생 정책에 집중하는 메시지로 ‘정치 싸움’ 피로도를 줄이는 전략이 유효하다."
      }
    ],
    "경제/산업": [
      {
        "title": "전북경제 위기, 에너지 절약으로 돌파해야",
        "source": "전북도민일보 - 전체",
        "link": "http://www.domin.co.kr/news/articleView.html?idxno=1550163",
        "published": "2026-03-29",
        "summary": "중동 전쟁 장기화로 고환율·고유가·고물가가 겹치며 전북 경제 전반의 부담이 커지고 있다는 진단이 나왔다. 수출기업부터 자영업, 농가까지 타격이 예상돼 에너지 절약과 민관 협력 대응이 필요하다는 주장이다.",
        "keywords": [
          "전북경제",
          "고유가",
          "고물가",
          "에너지 절약",
          "중동 전쟁"
        ],
        "ai_insight": "에너지 비용은 민생 체감도가 높아 ‘절감-지원-투자’(공공시설 절감, 취약계층·소상공인 지원, 지역 재생에너지 확대)로 공약 구조를 짜기 좋다. 농업은 난방·전력 의존도가 큰 시설원예 중심으로 에너지 효율·스마트 제어 지원을 전면에 세우면 반응이 빠르다."
      },
      {
        "title": "중동 전쟁 장기화에 기름값 2천원 시대 눈 앞, 시민, 농어민 등 전 부문 부담 가중",
        "source": "전북도민일보 - 전체",
        "link": "http://www.domin.co.kr/news/articleView.html?idxno=1550216",
        "published": "2026-03-29",
        "summary": "국제유가 상승과 정부의 석유 최고가격 상향 조정 영향으로 전북 지역 유류 가격이 리터당 2천원에 근접하고 있다. 소비자 부담뿐 아니라 농어업과 지역 산업 전반에 비용 압박이 확대될 것이란 우려가 제기된다.",
        "keywords": [
          "국제유가",
          "유류 가격",
          "전북",
          "농어민 부담",
          "정부 가격조정"
        ],
        "ai_insight": "유류비 급등은 농기계·물류비를 바로 자극하므로 ‘농업 경영비 완화’(면세유·물류지원·공동구매) 메시지를 강화할 필요가 있다. 캠페인은 주유비·난방비 같은 체감 지표를 수치로 제시해 민생 프레임을 선점하는 것이 효과적이다."
      },
      {
        "title": "새만금청, 현대차그룹 투자유치 특별성과 포상",
        "source": "정책브리핑 - 새만금개발청",
        "link": "https://www.korea.kr/briefing/pressReleaseView.do?newsId=156748393&call_from=rsslink",
        "published": "2026-03-11",
        "summary": "새만금개발청이 현대차그룹 9조원 투자유치 성과에 대해 특별성과 포상 제도를 신설하고 담당 공무원들에게 포상금과 표창을 수여했다. 대규모 투자 유치에 대한 성과 중심 문화를 독려하겠다는 취지다.",
        "keywords": [
          "새만금",
          "현대차그룹",
          "투자유치",
          "특별성과 포상",
          "공무원"
        ],
        "ai_insight": "투자 유치 ‘성과’가 주민 체감(고용·협력사·지역 상권)으로 연결되는지에 대한 설명이 필요하다. 캠페인은 지역 인력 우선채용, 협력사·소상공인 참여, 재생에너지 인프라 확충 같은 구체 KPI를 제시해 기대와 불신을 동시에 관리해야 한다."
      },
      {
        "title": "새만금청, 현대차그룹 9조 프로젝트 전담 '새만금 로봇수소추진본부' 출범",
        "source": "정책브리핑 - 새만금개발청",
        "link": "https://www.korea.kr/briefing/pressReleaseView.do?newsId=156748391&call_from=rsslink",
        "published": "2026-03-11",
        "summary": "새만금개발청이 현대차그룹 9조원 규모 프로젝트를 지원하기 위한 전담 T/F인 ‘새만금 로봇수소추진본부’를 출범시켰다. 로봇 제조, AI 데이터센터, AI 수소시티 등 미래산업 프로젝트의 투자 지원과 관계기관 협력을 체계화하는 것이 목표다.",
        "keywords": [
          "새만금",
          "로봇",
          "수소",
          "AI 데이터센터",
          "전담 T/F"
        ],
        "ai_insight": "대규모 프로젝트는 속도보다도 인허가·전력·인력·주거 같은 병목 관리가 성패다. 농업 관점에서는 수소·재생에너지 기반 전력 안정이 시설농업 에너지 비용 절감으로 이어질 수 있어, 에너지-농업 연계 실증사업을 함께 요구하면 실익이 커진다."
      },
      {
        "title": "새만금 크루즈 산업 활성화 협력 방안 논의",
        "source": "정책브리핑 - 새만금개발청",
        "link": "https://www.korea.kr/briefing/pressReleaseView.do?newsId=156748157&call_from=rsslink",
        "published": "2026-03-10",
        "summary": "새만금개발청이 전북자치도 등 관계기관과 크루즈 활성화 TFT 회의를 열고 신항만 임시 크루즈터미널 조성 계획을 협의했다. 예산, 운영 방식, CIQ(출입국·세관·검역) 기능 확보 등 실무 준비를 단계적으로 추진하기로 했다.",
        "keywords": [
          "새만금",
          "크루즈",
          "신항만",
          "임시터미널",
          "CIQ"
        ],
        "ai_insight": "관광 인프라 확장은 지역 소비를 늘릴 수 있지만, 지역상권 참여 구조가 없으면 효과가 제한된다. 농업·식품 관점에서는 로컬푸드·특산품 면세/판매 채널과 체험관광을 패키지로 설계해 ‘관광-농업 소득’ 연결고리를 만들 필요가 있다."
      },
      {
        "title": "숫자로 보는 새만금 그리고 현대차",
        "source": "정책브리핑 - 새만금개발청",
        "link": "https://www.korea.kr/news/policyNewsView.do?newsId=148960530&call_from=rsslink",
        "published": "2026-03-09",
        "summary": "정책브리핑이 현대차의 새만금 투자 규모와 사업 구성, 그리고 경제·고용 파급효과 전망을 수치로 정리했다. AI 데이터센터, 재생에너지, 로봇·부품 제조, 수소 관련 사업 등이 포함된다는 내용이다.",
        "keywords": [
          "새만금",
          "현대차 투자",
          "AI 데이터센터",
          "재생에너지",
          "고용"
        ],
        "ai_insight": "수치 중심 홍보는 기대를 키우는 만큼, 주민들은 ‘언제·어디서·몇 명이’라는 구체 일정과 채용 계획을 요구한다. 캠페인은 투자 효과를 지역 농생명·푸드테크와 연결해 ‘전북 산업 전환’ 메시지로 확장하되, 실질 참여(지역기업 물량, 교육 트랙) 장치를 제시해야 한다."
      },
      {
        "title": "새만금 로봇·AI·수소 생태계 조성",
        "source": "정책브리핑 - 새만금개발청",
        "link": "https://www.korea.kr/briefing/pressReleaseView.do?newsId=156746508&call_from=rsslink",
        "published": "2026-02-27",
        "summary": "정부와 현대차그룹이 새만금 투자협약을 통해 로봇 제조공장, AI 데이터센터, 그린수소 플랜트 등 로봇·AI·수소 산업 거점 조성을 추진한다고 밝혔다. 대규모 지방 투자와 재생에너지 기반 인프라를 결합해 미래산업 클러스터를 만들겠다는 계획이다.",
        "keywords": [
          "새만금",
          "로봇",
          "AI 데이터센터",
          "수소",
          "투자협약"
        ],
        "ai_insight": "대형 투자 이슈는 지역 여론을 양분시키므로, ‘지역 이익 환류’ 조건(채용, 협력사, 환경관리)을 명확히 걸어 메시지를 정리해야 한다. 농업 측면에선 재생에너지·수소 인프라가 전력단가 안정으로 이어질 수 있어, 시설농업·푸드테크 실증단지와의 연계를 요구하는 전략이 유효하다."
      }
    ],
    "기술/과학": [
      {
        "title": "새만금개발청 - 군산기계공업고등학교, 산·학·관 동반체제 구축 업무협약 체결",
        "source": "정책브리핑 - 새만금개발청",
        "link": "https://www.korea.kr/briefing/pressReleaseView.do?newsId=156751093&call_from=rsslink",
        "published": "2026-03-26",
        "summary": "새만금개발청이 군산기계공고와 산·학·관 협력 MOU를 체결해 AI·로봇 분야 실무 인재 양성과 취업 연계를 추진한다. 새만금 입주기업 수요에 맞춘 교육 프로그램 개발과 취업 매칭, 산학 연계를 강화하기로 했다.",
        "keywords": [
          "새만금개발청",
          "군산기계공고",
          "AI",
          "로봇",
          "인재양성"
        ],
        "ai_insight": "새만금의 투자·기업 유치가 ‘지역 청년 일자리’로 연결되는지 여부가 여론을 좌우한다. 캠페인은 교육-채용-정착(주거·교통)까지 전주기 지원을 공약으로 구체화하고, 농생명·푸드테크 기업과의 연계 트랙도 병행하면 파급력이 커진다."
      }
    ],
    "사회/문화": [
      {
        "title": "익산 한 도로서 무면허 운전 1t 트럭 SUV 차량과 충돌…4명 부상",
        "source": "전북도민일보 - 전체",
        "link": "http://www.domin.co.kr/news/articleView.html?idxno=1550263",
        "published": "2026-03-29",
        "summary": "익산 용안면 도로에서 1t 트럭과 SUV가 충돌해 농수로로 추락했고, SUV 탑승자 등 4명이 다쳤다. 트럭 운전자가 무면허였던 것으로 파악돼 경찰이 치상 혐의로 입건하고 경위를 조사 중이다.",
        "keywords": [
          "익산",
          "교통사고",
          "무면허 운전",
          "부상",
          "경찰 조사"
        ],
        "ai_insight": "지역 안전 이슈(무면허·교통사고)를 생활밀착형 공약(도로안전·단속·어린이 보호)으로 연결해 메시지를 만들 수 있다. 농촌 지역은 통학·통원 교통안전 요구가 높아 현장 간담회 소재로도 적합하다."
      },
      {
        "title": "‘유학생 8천명 시대’ 전북자치도, 겉도는 정착 정책… “통제를 넘어 이웃으로 포용해야“",
        "source": "전북도민일보 - 전체",
        "link": "http://www.domin.co.kr/news/articleView.html?idxno=1550202",
        "published": "2026-03-29",
        "summary": "전북 지역 외국인 유학생이 8,650명 수준으로 늘었지만, 학사관리 중심의 ‘통제’ 방식에 머물러 지역 정착을 돕는 정책이 부족하다는 연구 결과가 나왔다. 생계형 노동에 내몰리는 구조를 고려한 생활·취업·지역사회 연계 지원이 필요하다는 지적이다.",
        "keywords": [
          "전북",
          "외국인 유학생",
          "정착 정책",
          "노동",
          "지역사회 포용"
        ],
        "ai_insight": "지역 인구·일자리 이슈와 연결해 ‘유학생-지역기업-지자체’ 매칭(인턴·취업·정주) 공약을 설계할 수 있다. 농업·식품 분야는 인력난이 심해 계절·상시 인력 매칭과 교육 프로그램을 결합하면 실효성이 높다."
      },
      {
        "title": "전북 지역 의대 2027학년도에 38명 지역의사제로 선발",
        "source": "전북도민일보 - 전체",
        "link": "http://www.domin.co.kr/news/articleView.html?idxno=1550165",
        "published": "2026-03-29",
        "summary": "2027학년도부터 지역의사제가 본격 시행되며 전북에서는 총 38명을 지역의사제로 선발한다. 보건복지부가 운영 기준 고시안을 마련해 행정예고에 들어갔고, 증원 규모에 따라 지역의사 선발 인원이 산정된다.",
        "keywords": [
          "지역의사제",
          "전북",
          "의대 정원",
          "보건복지부",
          "의료인력"
        ],
        "ai_insight": "의료 공백 해소는 지방선거의 핵심 민생 의제라 ‘지역의사 정착’(근무환경·주거·가족지원) 패키지 공약이 필요하다. 농촌은 응급·분만·노인의료 수요가 높아, 보건지소-지역의사-원격협진 연계를 함께 제시하면 설득력이 커진다."
      },
      {
        "title": "전북자치도, 불리한 상황 속 스포츠·공연 복합형 돔구장 확보 위해 적극 대응 나섰다",
        "source": "전북도민일보 - 전체",
        "link": "http://www.domin.co.kr/news/articleView.html?idxno=1550196",
        "published": "2026-03-29",
        "summary": "전북자치도가 스포츠·공연 복합형 돔구장 확보를 위해 정부 용역 추진에 맞춰 적극 대응에 나섰다. 새만금 잠재력을 활용한 ‘아레나 건립’ 전략 등으로 대규모·중규모 돔구장 확보를 동시에 추진하려는 구상이다.",
        "keywords": [
          "전북자치도",
          "돔구장",
          "아레나",
          "새만금",
          "문화체육"
        ],
        "ai_insight": "대형 인프라는 찬반이 갈리므로 경제효과·재정 부담·교통 대책을 함께 제시하는 ‘조건부 찬성’ 설계가 필요하다. 농산물·지역식품 연계(푸드존, 로컬 브랜드)까지 묶으면 지역 산업 파급효과를 강화하는 캠페인 소재가 된다."
      },
      {
        "title": "애끓는 자임 추모관 유가족들 2년 가까운 외침에도 행정은 묵묵부답",
        "source": "전북도민일보 - 전체",
        "link": "http://www.domin.co.kr/news/articleView.html?idxno=1550147",
        "published": "2026-03-29",
        "summary": "전주 자임추모관 유가족들이 추모권 보장 등 문제 해결을 요구하며 재차 거리로 나섰다. 장기간 해결되지 않으면서 정치권에서도 사태 해결 필요성이 언급되는 등 갈등이 지속되고 있다.",
        "keywords": [
          "전주",
          "자임추모관",
          "유가족",
          "추모권",
          "행정 갈등"
        ],
        "ai_insight": "민원·갈등 이슈는 ‘조정자 역할’이 중요해, 캠페인은 피해자 권리 보장과 행정 책임(중재기구·일정 공개)을 구체화해야 한다. 지역 사회 신뢰 회복 메시지를 통해 ‘민생 해결형 리더십’을 부각하기 좋다."
      },
      {
        "title": "한국수자원공사 용담댐지사, 지역민과 합동 용담댐 깨끗한 물환경 조성 앞장",
        "source": "전북도민일보 - 진안",
        "link": "http://www.domin.co.kr/news/articleView.html?idxno=1549980",
        "published": "2026-03-26",
        "summary": "K-water 용담댐지사가 주민들과 함께 하천 정화활동을 진행하며 수질오염원을 줄이고 깨끗한 물환경 조성에 나섰다. 댐 주변 환경보전과 수질 관리 강화를 위해 청결지킴이 위촉과 교육도 병행했다.",
        "keywords": [
          "용담댐",
          "K-water",
          "수질 관리",
          "하천 정화",
          "주민 참여"
        ],
        "ai_insight": "수질·환경은 농업용수와 직결돼 ‘깨끗한 물’ 이슈를 농업 경쟁력(안전 농산물)과 연결할 수 있다. 지역 캠페인은 주민참여형 환경관리(감시·정화·인센티브)를 제도화하는 공약으로 신뢰를 얻기 좋다."
      },
      {
        "title": "진안군 거주 무주택 청년 월세 지원",
        "source": "전북도민일보 - 진안",
        "link": "http://www.domin.co.kr/news/articleView.html?idxno=1549979",
        "published": "2026-03-26",
        "summary": "진안군이 19~34세 무주택 청년을 대상으로 국토부 청년월세 지원사업 신청을 받는다. 소득·재산 기준을 충족하면 월 20만원씩 최대 24회 지원받을 수 있다.",
        "keywords": [
          "진안군",
          "청년월세",
          "주거 지원",
          "무주택",
          "국토부"
        ],
        "ai_insight": "청년 주거는 지방 정착의 핵심이라, 월세 지원과 함께 일자리·교통·돌봄을 묶은 정착 패키지로 공약화할 필요가 있다. 농업 분야는 청년농 주거(임대주택·농촌형 기숙사)와 영농 초기비용 지원을 연계하면 유입 효과가 커진다."
      },
      {
        "title": "진안군 다함께돌봄센터, 방과 후 돌봄 공백 해소 마중물",
        "source": "전북도민일보 - 진안",
        "link": "http://www.domin.co.kr/news/articleView.html?idxno=1549851",
        "published": "2026-03-25",
        "summary": "진안군 다함께돌봄센터가 맞벌이 가정 등을 대상으로 방과 후 돌봄 서비스를 제공하며 돌봄 공백 해소에 나서고 있다. 일시·긴급돌봄 체계를 구축하고 학기·방학 운영시간을 탄력적으로 운영한다.",
        "keywords": [
          "진안군",
          "다함께돌봄센터",
          "방과 후 돌봄",
          "맞벌이",
          "긴급돌봄"
        ],
        "ai_insight": "돌봄은 인구 유입과 직결돼 ‘아이 키우기 좋은 지역’ 메시지를 강화하는 소재다. 농촌은 돌봄 인프라가 취약해, 학교·마을회관·농협 등과 연계한 거점형 돌봄 모델을 제시하면 체감도가 높다."
      },
      {
        "title": "진안군, 특이민원 대응 모의훈련",
        "source": "전북도민일보 - 진안",
        "link": "http://www.domin.co.kr/news/articleView.html?idxno=1549850",
        "published": "2026-03-25",
        "summary": "진안군이 폭언·폭행 등 위법행위에 대비해 민원 담당 공무원을 보호하는 모의훈련을 실시했다. 비상벨 작동, 녹음·녹화 고지, 경찰 인계 등 단계별 대응 절차를 점검했다.",
        "keywords": [
          "진안군",
          "민원",
          "공무원 보호",
          "모의훈련",
          "경찰"
        ],
        "ai_insight": "민원 안전은 행정 신뢰와 연결돼, ‘안전한 민원창구’ 개선(보안장비·상담 분리·법률지원)을 공약으로 구체화할 수 있다. 농업 현장 민원(보조금·시설 인허가)도 많아, 상담·조정 기능을 강화하면 갈등 비용을 줄인다."
      },
      {
        "title": "진안 용담호 광역상수원 지킴이 활동 돌입",
        "source": "전북도민일보 - 진안",
        "link": "http://www.domin.co.kr/news/articleView.html?idxno=1549787",
        "published": "2026-03-25",
        "summary": "용담호 광역상수원 수질 보호를 위해 주민 참여형 지킴이 42명이 선발돼 9월까지 활동에 들어갔다. 유입하천 오염행위 감시, 쓰레기 투기 계도 등 현장 중심 수질관리 활동을 수행한다.",
        "keywords": [
          "용담호",
          "광역상수원",
          "수질 보호",
          "지킴이",
          "주민 참여"
        ],
        "ai_insight": "주민참여형 수질관리는 지속 가능성이 높아, 농업·관광과 결합한 ‘환경지킴이 일자리’ 모델로 확장할 수 있다. 캠페인에서는 용담호 수질 개선 성과를 데이터로 공개하고 참여 인센티브를 제도화하는 방안을 제시하면 설득력이 커진다."
      },
      {
        "title": "한국수자원공사 용담댐지사, 운영 소통회의...‘홍수 등 댐 운영 등 지역사회와 협조체계 구축’",
        "source": "전북도민일보 - 진안",
        "link": "http://www.domin.co.kr/news/articleView.html?idxno=1549679",
        "published": "2026-03-24",
        "summary": "용담댐지사가 관계기관과 지자체, 주민대표가 참여하는 운영 소통회의를 열어 댐 운영방안과 제약사항 점검, 협조체계 구축을 논의했다. 홍수 대응과 물관리 정책 방향에 맞춰 협력·소통 기반을 강화하겠다는 취지다.",
        "keywords": [
          "용담댐",
          "홍수 대응",
          "소통회의",
          "지자체 협력",
          "물관리"
        ],
        "ai_insight": "기후위기 국면에서 홍수·가뭄 대응은 지역 핵심 의제라, 예경보·대피·저수 관리 등 ‘재난 대응 체계’ 공약으로 연결할 수 있다. 농업은 용수 안정성이 중요하므로, 관개 정보 공개와 수요관리(절수·스마트 관개) 지원을 함께 제시하는 것이 효과적이다."
      },
      {
        "title": "새만금청, 농생명용지 굴착공사장 안전관리 강화",
        "source": "정책브리핑 - 새만금개발청",
        "link": "https://www.korea.kr/briefing/pressReleaseView.do?newsId=156749389&call_from=rsslink",
        "published": "2026-03-17",
        "summary": "새만금개발청이 국토부 등과 합동으로 농생명용지 굴착공사장 안전점검을 실시해 지하 안전사고 예방을 강화했다. 흙막이·차수공법, 지반침하 계측 관리, 품질관리 문서 등을 집중 점검했다.",
        "keywords": [
          "새만금",
          "농생명용지",
          "굴착공사",
          "지하안전",
          "합동점검"
        ],
        "ai_insight": "대형 개발사업은 안전·품질 이슈가 곧 신뢰로 이어지므로 점검 결과 공개와 상시 감시체계를 공약화하면 효과적이다. 농업 관점에서는 농생명용지 조성이 실제로 어떤 작목·가공·수출로 이어지는지 로드맵을 함께 제시해야 ‘개발 체감’이 생긴다."
      },
      {
        "title": "새만금청, 국립새만금수목원 찾아 현장행정 펼쳐",
        "source": "정책브리핑 - 새만금개발청",
        "link": "https://www.korea.kr/briefing/pressReleaseView.do?newsId=156749172&call_from=rsslink",
        "published": "2026-03-16",
        "summary": "새만금개발청이 국립새만금수목원 조성 현장을 찾아 진입도로 개선 등 애로사항을 듣고 건설현장 안전점검을 실시했다. 수목원은 해안형 수목원으로 2027년 개원을 목표로 공사가 진행 중이다.",
        "keywords": [
          "국립새만금수목원",
          "현장행정",
          "진입도로",
          "안전점검",
          "관광"
        ],
        "ai_insight": "관광 인프라는 교통·안전이 함께 따라와야 주민 수용성이 높아진다. 농촌 관광과 연계해 로컬푸드·체험농장·숙박까지 묶는 지역상권 패키지를 설계하면 농업 소득 다변화에도 활용 가능하다."
      }
    ],
    "농업/스마트팜": [
      {
        "title": "진안군, AI 교육으로 농업인 역량 키운다",
        "source": "전북도민일보 - 진안",
        "link": "http://www.domin.co.kr/news/articleView.html?idxno=1550228",
        "published": "2026-03-29",
        "summary": "진안군이 4~9월 농업인을 대상으로 AI 활용 교육을 운영해 온라인 홍보 글 작성, 상세페이지 제작, 숏폼 영상 제작 등 실무 역량을 강화한다. 기초·심화 과정으로 나눠 총 10회 진행하며, 관심 농업인을 모집한다.",
        "keywords": [
          "진안군",
          "농업인 교육",
          "AI",
          "SNS 홍보",
          "숏폼"
        ],
        "ai_insight": "스마트팜·농산물 직거래에서 콘텐츠 마케팅이 성패를 좌우하므로, 교육을 ‘판매 전환’까지 연결(공동브랜드·라이브커머스)하면 효과가 커진다. 캠페인에서는 청년농·귀농 유입과 디지털 역량 강화 공약으로 확장하기 좋다."
      },
      {
        "title": "새만금, 피지컬 AI와 농생명 결합한 혁신적 푸드테크 허브 논의",
        "source": "정책브리핑 - 새만금개발청",
        "link": "https://www.korea.kr/briefing/pressReleaseView.do?newsId=156749839&call_from=rsslink",
        "published": "2026-03-19",
        "summary": "새만금개발청이 ‘새만금 푸드테크 허브 조성 전략 토론회’를 열고 피지컬 AI와 농생명 자원을 결합한 푸드테크 클러스터 방향을 논의했다. 종자-생산-가공-수출까지 연결되는 전주기 산업 밸리 구상과 기관·대학·기업 집적이 핵심으로 제시됐다.",
        "keywords": [
          "새만금",
          "푸드테크",
          "피지컬 AI",
          "농생명",
          "클러스터"
        ],
        "ai_insight": "농업·산업을 동시에 건드리는 의제라 ‘새만금 푸드테크’의 지역 환류(농가 계약재배, 가공 일자리, 물류) 설계를 강조해야 한다. 농업 현장에서는 데이터 기반 재배·가공 품질관리 도입을 지원하면 스마트팜 확산과 함께 실질 소득 개선으로 이어질 수 있다."
      },
      {
        "title": "송미령 농식품부 장관, 전북 김제시 죽산면 「다시온(ON:溫)마을」 사업 현장 간담회 개최",
        "source": "정책브리핑 - 농림축산식품부",
        "link": "https://www.korea.kr/briefing/pressReleaseView.do?newsId=156751470&call_from=rsslink",
        "published": "2026-03-27",
        "summary": "농식품부 장관이 전북 김제 죽산면 ‘다시온 마을’ 현장을 방문해 추진 현황을 점검하고 주민·관계자의 의견을 청취했다. 농촌 활력 증진을 위해 일자리·창업·관광·체류 등 재생 인프라를 연계하는 프로젝트의 시범지구 운영이 진행 중이다.",
        "keywords": [
          "농식품부",
          "김제",
          "다시온 마을",
          "농촌재생",
          "청년 창업"
        ],
        "ai_insight": "농촌재생 사업은 ‘체류-일자리-창업’으로 연결될 때 성과가 나므로, 지역 상권·농산물 판매와 묶는 실행계획이 필요하다. 캠페인에서는 시범지구 성과지표(방문객, 창업, 고용)를 공개하고 확대 대상(진안 등) 로드맵을 제시하면 설득력이 높다."
      }
    ]
  }
}